frontend/dist/app.js
frontend/dist/file.js
frontend/dist/notebook.js
frontend/dist/styles.css
frontend/dist/tree.js
notebookx-0.2.1.dist-info/licenses/LICENSE
server/__init__.py
server/logger.py
server/run.py
server/src/__init__.py
server/src/server.py
server/src/handlers/__init__.py
server/src/handlers/base_handler.py
server/src/handlers/file_handler.py
server/src/handlers/kernel_handler.py
server/src/handlers/notebook_handler.py
server/src/handlers/packages_handler.py
server/src/handlers/runningkernels.py
server/src/handlers/websocket_handler.py
server/src/managers/kernel_manager.py
server/src/managers/session_manager.py
server/src/utils/__init__.py
server/src/utils/excluded_dirs.py
server/src/utils/file_utils.py
server/src/utils/help.py
server/templates/base.html
server/templates/error.html
server/templates/file.html
server/templates/home.html
server/templates/notebook.html
server/templates/packages.html
server/templates/running.html
server/templates/toolbar.html
notebookx-0.2.1.dist-info/METADATA
notebookx-0.2.1.dist-info/WHEEL
notebookx-0.2.1.dist-info/entry_points.txt
notebookx-0.2.1.dist-info/top_level.txt
notebookx-0.2.1.dist-info/RECORD
